{
  "articles": {
    "explaining_this_site": {
      "id": "explaining_this_site",
      "title": "How (And Why) I Made This Site Entirely In Vanilla",
      "description": "Hand writing HTML in 2024 because I am not well in the head",
      "relativeUrl": "/pages/articles/explaining_this_site",
      "image": "https://mostlyfocused.com/images/explaining_this_site/preview.png",
      "level": 0,
      "publishedAt": "2024-07-15T07:35:40+03:00",
      "modifiedAt": "2024-07-15T07:35:40+03:00",
      "topics": [
        "js",
        "html",
        "css",
        "web-standards",
        "updates"
      ]
    },
    "html_dialog_tags": {
      "id": "html_dialog_tags",
      "title": "How To Make Modals With The HTML Dialog Tag",
      "description": "Use the HTML dialog tag to make modals, with a11y features built in, in any framework!",
      "relativeUrl": "/pages/articles/html_dialog_tags",
      "image": "https://mostlyfocused.com/images/html_dialog_tags/preview.png",
      "level": 0,
      "publishedAt": "2024-07-15T19:21:15.248Z",
      "modifiedAt": "2024-07-15T19:21:15.248Z",
      "topics": [
        "html",
        "css",
        "js",
        "react",
        "web-standards",
        "a11y"
      ]
    },
    "stop_controlling_react_forms": {
      "id": "stop_controlling_react_forms",
      "title": "Stop Controlling EVERY Form In React, Use FormData!",
      "description": "The FormData API is available in all browsers and it simplifies everything.",
      "relativeUrl": "/pages/articles/stop_controlling_react_forms",
      "image": "https://mostlyfocused.com/images/stop_controlling_react_forms/preview.png",
      "level": 0,
      "publishedAt": "2024-04-09T07:35:40+03:00",
      "modifiedAt": "2024-04-09T07:35:40+03:00",
      "topics": [
        "html",
        "js",
        "forms",
        "react",
        "web-standards"
      ]
    }
  },
  "allTopics": [
    "a11y",
    "css",
    "forms",
    "html",
    "js",
    "react",
    "updates",
    "web-standards"
  ],
  "publishOrder": [
    "stop_controlling_react_forms",
    "explaining_this_site",
    "html_dialog_tags"
  ]
}